tencentcloud_im/__init__.py
tencentcloud_im/tcim.json
tencentcloud_im/tcim_client.py
tencentcloud_sdk_python_im-0.9.4.dist-info/LICENSE
tencentcloud_sdk_python_im-0.9.4.dist-info/METADATA
tencentcloud_sdk_python_im-0.9.4.dist-info/WHEEL
tencentcloud_sdk_python_im-0.9.4.dist-info/top_level.txt
tencentcloud_sdk_python_im-0.9.4.dist-info/RECORD
