Metadata-Version: 2.1
Name: tencentcloud-sdk-python-im
Version: 0.9.4
Summary: Python API Client for Tencent Cloud Instant Messaging Service
Home-page: https://github.com/pinclr/tencentcloud-sdk-python-im
Author: Pinclr Tech
Author-email: Pinclr <coding@pinclr.com>
Classifier: Programming Language :: Python :: 3
Classifier: License :: OSI Approved :: Apache Software License
Classifier: Operating System :: OS Independent
Requires-Python: >=3.6
License-File: LICENSE
Requires-Dist: tls-sig-api-v2 (>=1.1)
